acoupi_birdnet/__init__.py
acoupi_birdnet/configuration.py
acoupi_birdnet/model.py
acoupi_birdnet/program.py
acoupi_birdnet-0.1.1.dist-info/METADATA
acoupi_birdnet-0.1.1.dist-info/WHEEL
acoupi_birdnet-0.1.1.dist-info/licenses/LICENSE
acoupi_birdnet-0.1.1.dist-info/RECORD
