Metadata-Version: 2.4
Name: acoupi_birdnet
Version: 0.1.1
Summary: An acoupi-compatible BirdNET model implementation
Author-email: Aude Vuilliomenet <aude.vuilliomenet.18@ucl.ac.uk>, Santiago Martinez <santiago.balvanera.20@ucl.ac.uk>
License: MIT
License-File: LICENSE
Requires-Python: <3.13,>=3.9
Requires-Dist: acoupi>=0.3.0
Requires-Dist: audioclass[birdnet]>=0.2.2
